chobo/__init__.py
chobo-0.99.11.dist-info/LICENSE
chobo-0.99.11.dist-info/METADATA
chobo-0.99.11.dist-info/WHEEL
chobo-0.99.11.dist-info/top_level.txt
chobo-0.99.11.dist-info/RECORD
