Metadata-Version: 2.1
Name: chobo
Version: 0.99.11
Summary: A Python package for graphical displays
Author-email: Choong-Soo Lee <choongsoo.lee@gmail.com>
Project-URL: Homepage, https://github.com/choongsoo/chobo
Project-URL: Bug Tracker, https://github.com/choongsoo/chobo/issues
Classifier: Programming Language :: Python :: 3
Classifier: License :: OSI Approved :: GNU General Public License v3 (GPLv3)
Classifier: Operating System :: OS Independent
Requires-Python: >=3.7
License-File: LICENSE
Requires-Dist: pygame >=2.5.0
